{
  "project_info": {
    "project_number": "332937749798",
    "project_id": "dali-lab-1518041067726"
  },
  "client": [
    {
      "client_info": {
        "mobilesdk_app_id": "1:332937749798:android:beac6ae81b4a1186",
        "android_client_info": {
          "package_name": "com.DALI.DaliLabApp"
        }
      },
      "oauth_client": [
        {
          "client_id": "332937749798-fr6c82irpv5h9rfrag2s9ss9benvife6.apps.googleusercontent.com",
          "client_type": 1,
          "android_info": {
            "package_name": "com.DALI.DaliLabApp",
            "certificate_hash": "883a41480014c4a874095d9d3cca95405673ab8f"
          }
        },
        {
          "client_id": "332937749798-bthkb1i43tjhmgg6b7u5f2u6du8q6rut.apps.googleusercontent.com",
          "client_type": 3
        }
      ],
      "api_key": [
        {
          "current_key": "AIzaSyDHVOOI4DVBogTVE4YTRUJvL1M2JQWUjqo"
        }
      ],
      "services": {
        "analytics_service": {
          "status": 1
        },
        "appinvite_service": {
          "status": 1,
          "other_platform_oauth_client": []
        },
        "ads_service": {
          "status": 1
        }
      }
    }
  ],
  "configuration_version": "1"
}